<laserDevice>
  <jobSentText>Job was sent as &apos;$jobname&apos;
Please:
-Close the lid
-Turn on the Ventilation
-And press &apos;start&apos; on the Lasercutter $name</jobSentText>
  <jobPrefix>visicut </jobPrefix>
  <laserCutter class="com.t_oster.liblasercut.drivers.EpilogZing">
    <hostname>137.226.72.26</hostname>
    <port>515</port>
    <autofocus>false</autofocus>
    <bedWidth>600.0</bedWidth>
    <bedHeight>300.0</bedHeight>
  </laserCutter>
  <cameraURL>http://137.226.72.45:8080/image</cameraURL>
  <thumbnailPath>Epilog_32_ZING.png</thumbnailPath>
  <description>Epilog Zing 6030 in room 2214</description>
  <name>Epilog ZING</name>
</laserDevice>
